mal_gui/__init__.py
mal_gui/app.py
mal_gui/association_table_view.py
mal_gui/connection_dialog.py
mal_gui/connection_item.py
mal_gui/file_utils.py
mal_gui/main_window.py
mal_gui/model_scene.py
mal_gui/model_view.py
mal_gui/assets_container/__init__.py
mal_gui/assets_container/assets_container.py
mal_gui/assets_container/assets_container_rectangle_box.py
mal_gui/docked_windows/__init__.py
mal_gui/docked_windows/asset_relations_window.py
mal_gui/docked_windows/attack_steps_window.py
mal_gui/docked_windows/draggable_tree_view.py
mal_gui/docked_windows/item_details_window.py
mal_gui/docked_windows/properties_window.py
mal_gui/docked_windows/style_configuration.py
mal_gui/images/WebsiteLink.txt
mal_gui/images/application.png
mal_gui/images/assetContainer.png
mal_gui/images/assetContainerMinusSymbol.png
mal_gui/images/assetContainerPlusSymbol.png
mal_gui/images/attacker.png
mal_gui/images/client.png
mal_gui/images/connectionRule.png
mal_gui/images/container.png
mal_gui/images/copyIcon.png
mal_gui/images/credentials.png
mal_gui/images/cutIcon.png
mal_gui/images/datastore.png
mal_gui/images/deleteIcon.png
mal_gui/images/eyeHide.png
mal_gui/images/eyeUnhide.png
mal_gui/images/firewall.png
mal_gui/images/fitToView.png
mal_gui/images/group.png
mal_gui/images/hardware.png
mal_gui/images/hardwareVulnerability.png
mal_gui/images/host.png
mal_gui/images/identity.png
mal_gui/images/idps.png
mal_gui/images/information.png
mal_gui/images/network.png
mal_gui/images/pasteIcon.png
mal_gui/images/physicalZone.png
mal_gui/images/privileges.png
mal_gui/images/redoIcon.png
mal_gui/images/rgbColor.png
mal_gui/images/routingFirewall.png
mal_gui/images/softwareProduct.png
mal_gui/images/softwareVulnerability.png
mal_gui/images/undoIcon.png
mal_gui/images/unknown.png
mal_gui/images/user.png
mal_gui/images/zoomIn.png
mal_gui/images/zoomOut.png
mal_gui/object_explorer/__init__.py
mal_gui/object_explorer/asset_factory.py
mal_gui/object_explorer/asset_item.py
mal_gui-2.0.0.dist-info/METADATA
mal_gui-2.0.0.dist-info/WHEEL
mal_gui-2.0.0.dist-info/entry_points.txt
mal_gui-2.0.0.dist-info/top_level.txt
mal_gui-2.0.0.dist-info/RECORD
