Metadata-Version: 2.4
Name: mal-gui
Version: 2.0.0
Summary: A graphical user interface tool used to create MAL instance models.
Author-email: Akash Sinha <aksinha@kth.se>, Andrei Buhaiu <buhaiu@kth.se>, Joakim Loxdal <loxdal@kth.se>, Sandor Berglund <sandorb@kth.se>
Requires-Python: <=3.13,>=3.10
Requires-Dist: networkx==3.2.1
Requires-Dist: numpy==1.26.4
Requires-Dist: PySide6~=6.8.1
Requires-Dist: PySide6_Addons~=6.8.1
Requires-Dist: PySide6_Essentials~=6.8.1
Requires-Dist: shiboken6~=6.8.1
Requires-Dist: mal-toolbox==2.*
Requires-Dist: mal-simulator==2.*
Requires-Dist: qt-material==2.14
Requires-Dist: appdirs==1.4.4
